nspfile/__init__.py
nspfile-0.2.0.dist-info/licenses/LICENSE
nspfile-0.2.0.dist-info/METADATA
nspfile-0.2.0.dist-info/WHEEL
nspfile-0.2.0.dist-info/top_level.txt
nspfile-0.2.0.dist-info/RECORD
