Metadata-Version: 2.4
Name: nspfile
Version: 0.2.0
Summary: KayPENTAX CSL NSP Audio File Format Reader
License-Expression: GPL-2.0
Project-URL: Repository, https://github.com/tikuma-lsuhsc/python-nspfile
Project-URL: Issues, https://github.com/tikuma-lsuhsc/python-nspfile/issues
Project-URL: Pull_Requests, https://github.com/tikuma-lsuhsc/python-nspfile/pulls
Keywords: multimedia
Classifier: Development Status :: 4 - Beta
Classifier: Topic :: Multimedia :: Sound/Audio
Classifier: Programming Language :: Python :: 3
Requires-Python: >=3.10
License-File: LICENSE
Requires-Dist: numpy
Dynamic: license-file
